zns_discord_bot/__init__.py
zns_discord_bot/logger_base.py
zns_discord_bot/zns_discord_bot.py
zns_discord_bot/components/__init__.py
zns_discord_bot/components/easy_embed.py
zns_discord_bot/utils/__init__.py
zns_discord_bot/utils/channel_utils.py
zns_discord_bot/utils/message_utils.py
zns_discord_bot-1.0.13.dist-info/LICENSE
zns_discord_bot-1.0.13.dist-info/METADATA
zns_discord_bot-1.0.13.dist-info/WHEEL
zns_discord_bot-1.0.13.dist-info/top_level.txt
zns_discord_bot-1.0.13.dist-info/RECORD
