Metadata-Version: 2.1
Name: zns-discord-bot
Version: 1.0.13
Summary: A Discord bot library that integrates many functionalities for Python
Home-page: https://github.com/Zennisch/zns-discord-bot
Author: Zennisch
Author-email: zennisch@gmail.com
Requires-Python: >=3.10
License-File: LICENSE
Requires-Dist: discord.py
Requires-Dist: zns-logging
